xpi/__init__.py
xpi/xpi.py
xpi-0.0.1.dist-info/LICENSE
xpi-0.0.1.dist-info/METADATA
xpi-0.0.1.dist-info/WHEEL
xpi-0.0.1.dist-info/top_level.txt
xpi-0.0.1.dist-info/RECORD
